werkflow_docker/__init__.py
werkflow_docker/docker.py
werkflow_docker/api/__init__.py
werkflow_docker/api/docker_client.py
werkflow_docker/cli/__init__.py
werkflow_docker/cli/build_argument.py
werkflow_docker/cli/build_cache_image.py
werkflow_docker/cli/build_envar.py
werkflow_docker/cli/build_host.py
werkflow_docker/cli/build_label.py
werkflow_docker/cli/build_options.py
werkflow_docker/cli/build_secret.py
werkflow_docker/images/__init__.py
werkflow_docker/images/directive.py
werkflow_docker/images/image.py
werkflow_docker/images/layers/__init__.py
werkflow_docker/images/layers/add.py
werkflow_docker/images/layers/arg.py
werkflow_docker/images/layers/cmd.py
werkflow_docker/images/layers/copy.py
werkflow_docker/images/layers/entrypoint.py
werkflow_docker/images/layers/env.py
werkflow_docker/images/layers/expose.py
werkflow_docker/images/layers/healthcheck.py
werkflow_docker/images/layers/label.py
werkflow_docker/images/layers/maintainer.py
werkflow_docker/images/layers/onbuild.py
werkflow_docker/images/layers/run.py
werkflow_docker/images/layers/shell.py
werkflow_docker/images/layers/stage.py
werkflow_docker/images/layers/stopsignal.py
werkflow_docker/images/layers/user.py
werkflow_docker/images/layers/volume.py
werkflow_docker/images/layers/workdir.py
werkflow_docker/images/layers/mount_types/__init__.py
werkflow_docker/images/layers/mount_types/bind_mount.py
werkflow_docker/images/layers/mount_types/cache_mount.py
werkflow_docker/images/layers/mount_types/secret_mount.py
werkflow_docker/images/layers/mount_types/ssh_mount.py
werkflow_docker/images/layers/mount_types/tmpfs_mount.py
werkflow_docker/images/memory_file/__init__.py
werkflow_docker/images/memory_file/memory_file.py
werkflow_docker/images/queries/__init__.py
werkflow_docker/images/queries/layer_query.py
werkflow_docker-0.3.2.dist-info/licenses/LICENSE
werkflow_docker-0.3.2.dist-info/METADATA
werkflow_docker-0.3.2.dist-info/WHEEL
werkflow_docker-0.3.2.dist-info/top_level.txt
werkflow_docker-0.3.2.dist-info/RECORD
